[
    {
        "base_point": [
            1374.7969970703125,
            976.6657104492188
        ],
        "next_point": [
            458.2656555175781,
            999.475341796875
        ]
    },
    {
        "base_point": [
            1433.272705078125,
            924.4609375
        ],
        "next_point": [
            512.39501953125,
            945.9600219726562
        ]
    },
    {
        "base_point": [
            1376.5389404296875,
            979.4030151367188
        ],
        "next_point": [
            459.8416748046875,
            1000.304931640625
        ]
    },
    {
        "base_point": [
            1320.192138671875,
            869.18408203125
        ],
        "next_point": [
            404.35205078125,
            895.1040649414062
        ]
    },
    {
        "base_point": [
            1104.8143310546875,
            798.7509155273438
        ],
        "next_point": [
            186.62403869628906,
            826.1224365234375
        ]
    },
    {
        "base_point": [
            1402.800048828125,
            834.0000610351562
        ],
        "next_point": [
            484.8000183105469,
            859.2000122070312
        ]
    },
    {
        "base_point": [
            1312.800048828125,
            1089.60009765625
        ],
        "next_point": [
            399.6000061035156,
            1112.4000244140625
        ]
    },
    {
        "base_point": [
            1200.6146240234375,
            1011.9169311523438
        ],
        "next_point": [
            286.1568298339844,
            1040.9473876953125
        ]
    },
    {
        "base_point": [
            1375.94189453125,
            1042.7059326171875
        ],
        "next_point": [
            462.23046875,
            1064.2049560546875
        ]
    },
    {
        "base_point": [
            1398.4361572265625,
            823.6340942382812
        ],
        "next_point": [
            480.2458801269531,
            848.517333984375
        ]
    },
    {
        "base_point": [
            1316.4000244140625,
            871.2000122070312
        ],
        "next_point": [
            400.8000183105469,
            896.4000244140625
        ]
    },
    {
        "base_point": [
            1396.800048828125,
            819.3600463867188
        ],
        "next_point": [
            479.52001953125,
            845.280029296875
        ]
    },
    {
        "base_point": [
            1465.3441162109375,
            976.320068359375
        ],
        "next_point": [
            544.320068359375,
            995.328125
        ]
    },
    {
        "base_point": [
            1373.7601318359375,
            976.320068359375
        ],
        "next_point": [
            457.9200439453125,
            998.7841186523438
        ]
    },
    {
        "base_point": [
            1152.0924072265625,
            1050.0712890625
        ],
        "next_point": [
            236.3904571533203,
            1082.41943359375
        ]
    },
    {
        "base_point": [
            1403.412841796875,
            833.58740234375
        ],
        "next_point": [
            485.2225036621094,
            858.4705810546875
        ]
    },
    {
        "base_point": [
            1319.8052978515625,
            1074.95458984375
        ],
        "next_point": [
            406.09393310546875,
            1098.8424072265625
        ]
    },
    {
        "base_point": [
            1458.35498046875,
            949.543212890625
        ],
        "next_point": [
            537.477294921875,
            971.0422973632812
        ]
    },
    {
        "base_point": [
            1089.2872314453125,
            899.378662109375
        ],
        "next_point": [
            168.4095458984375,
            928.0441284179688
        ]
    },
    {
        "base_point": [
            1261.2000732421875,
            1098.0
        ],
        "next_point": [
            349.20001220703125,
            1124.4000244140625
        ]
    },
    {
        "base_point": [
            1385.8560791015625,
            820.800048828125
        ],
        "next_point": [
            466.56005859375,
            846.7200927734375
        ]
    },
    {
        "base_point": [
            1410.0482177734375,
            839.80810546875
        ],
        "next_point": [
            491.4432678222656,
            864.6913452148438
        ]
    },
    {
        "base_point": [
            1373.552978515625,
            1042.6063232421875
        ],
        "next_point": [
            457.8509826660156,
            1062.512939453125
        ]
    },
    {
        "base_point": [
            1326.27490234375,
            1089.8843994140625
        ],
        "next_point": [
            413.06121826171875,
            1112.279296875
        ]
    },
    {
        "base_point": [
            1448.20263671875,
            961.4871215820312
        ],
        "next_point": [
            528.519287109375,
            982.3889770507812
        ]
    },
    {
        "base_point": [
            1403.412841796875,
            833.0897827148438
        ],
        "next_point": [
            483.72955322265625,
            859.963623046875
        ]
    },
    {
        "base_point": [
            998.4000244140625,
            1042.800048828125
        ],
        "next_point": [
            70.56000518798828,
            1085.760009765625
        ]
    },
    {
        "base_point": [
            994.800048828125,
            1006.800048828125
        ],
        "next_point": [
            67.20000457763672,
            1047.60009765625
        ]
    },
    {
        "base_point": [
            1397.9521484375,
            820.800048828125
        ],
        "next_point": [
            480.384033203125,
            846.7200927734375
        ]
    },
    {
        "base_point": [
            1364.428955078125,
            796.2625122070312
        ],
        "next_point": [
            447.8976745605469,
            823.2192993164062
        ]
    },
    {
        "base_point": [
            1320.8834228515625,
            1076.1986083984375
        ],
        "next_point": [
            406.4256591796875,
            1099.0081787109375
        ]
    },
    {
        "base_point": [
            1134.6741943359375,
            1040.1180419921875
        ],
        "next_point": [
            216.48388671875,
            1074.9544677734375
        ]
    },
    {
        "base_point": [
            1311.344970703125,
            1087.3961181640625
        ],
        "next_point": [
            395.6429748535156,
            1112.279296875
        ]
    },
    {
        "base_point": [
            1364.5950927734375,
            797.2579345703125
        ],
        "next_point": [
            447.897705078125,
            824.1318359375
        ]
    },
    {
        "base_point": [
            1424.314697265625,
            895.79541015625
        ],
        "next_point": [
            504.6314392089844,
            916.6973266601562
        ]
    },
    {
        "base_point": [
            1397.44091796875,
            827.7150268554688
        ],
        "next_point": [
            480.1463623046875,
            852.7973022460938
        ]
    },
    {
        "base_point": [
            1244.0,
            1118.0
        ],
        "next_point": [
            332.0,
            1146.0
        ]
    },
    {
        "base_point": [
            1136.4000244140625,
            699.6000366210938
        ],
        "next_point": [
            222.00001525878906,
            723.6000366210938
        ]
    },
    {
        "base_point": [
            1363.39208984375,
            794.8800659179688
        ],
        "next_point": [
            449.280029296875,
            820.800048828125
        ]
    },
    {
        "base_point": [
            1148.7745361328125,
            1059.6097412109375
        ],
        "next_point": [
            232.24322509765625,
            1092.787353515625
        ]
    },
    {
        "base_point": [
            1134.6741943359375,
            1060.0245361328125
        ],
        "next_point": [
            218.9722137451172,
            1092.3726806640625
        ]
    },
    {
        "base_point": [
            1423.3193359375,
            895.79541015625
        ],
        "next_point": [
            502.6407470703125,
            918.1903076171875
        ]
    },
    {
        "base_point": [
            1408.1904296875,
            820.5486450195312
        ],
        "next_point": [
            490.8959045410156,
            845.6309204101562
        ]
    },
    {
        "base_point": [
            1451.1885986328125,
            960.292724609375
        ],
        "next_point": [
            530.3109130859375,
            981.7918090820312
        ]
    },
    {
        "base_point": [
            1386.69140625,
            816.9654541015625
        ],
        "next_point": [
            469.3968200683594,
            842.0477294921875
        ]
    },
    {
        "base_point": [
            1235.0,
            1088.0
        ],
        "next_point": [
            322.0,
            1116.0
        ]
    },
    {
        "base_point": [
            1232.0,
            1088.0
        ],
        "next_point": [
            319.0,
            1117.0
        ]
    },
    {
        "base_point": [
            1259.0,
            1088.0
        ],
        "next_point": [
            346.0,
            1115.0
        ]
    },
    {
        "base_point": [
            998.0,
            1043.0
        ],
        "next_point": [
            71.0,
            1086.0
        ]
    },
    {
        "base_point": [
            999.3600463867188,
            1039.6800537109375
        ],
        "next_point": [
            70.56000518798828,
            1082.8800048828125
        ]
    }
]